{
 "based_on": "date",
 "chart_name": "Total Volume in Ton-1",
 "chart_type": "Sum",
 "creation": "2022-04-19 12:23:11.893257",
 "docstatus": 0,
 "doctype": "Dashboard Chart",
 "document_type": "ECTA Dispatches",
 "filters_json": "[]",
 "group_by_type": "Count",
 "idx": 0,
 "is_public": 1,
 "is_standard": 1,
 "last_synced_on": "2022-04-19 12:30:16.662768",
 "modified": "2022-04-19 12:35:06.517857",
 "modified_by": "Administrator",
 "module": "Ecta Dispatch",
 "name": "Total Volume in Ton-1",
 "number_of_groups": 0,
 "owner": "Administrator",
 "time_interval": "Monthly",
 "timeseries": 1,
 "timespan": "Last Year",
 "type": "Bar",
 "use_report_chart": 0,
 "value_based_on": "volume_in_ton",
 "y_axis": []
}